octotail/__init__.py
octotail/browser.py
octotail/cli.py
octotail/fmt.py
octotail/gh.py
octotail/git.py
octotail/main.py
octotail/manager.py
octotail/mitm.py
octotail/msg.py
octotail/streamer.py
octotail/utils.py
octotail/x.py
octotail-1.0.16.dist-info/METADATA
octotail-1.0.16.dist-info/WHEEL
octotail-1.0.16.dist-info/entry_points.txt
octotail-1.0.16.dist-info/RECORD
