Metadata-Version: 2.3
Name: octotail
Version: 1.0.16
Summary: Live tail GitHub Actions runs on git push
Project-URL: Documentation, https://github.com/getbettr/octotail#readme
Project-URL: Repository, https://github.com/getbettr/octotail
Project-URL: Issues, https://github.com/getbettr/octotail/issues
Project-URL: Homepage, https://getbetter.ro/projects/#octotail
Author-email: Rareș Cosma <rares@getbetter.ro>
License: Unlicense
Keywords: codecrafters,git,github-actions,post-receive,tail
Classifier: Development Status :: 3 - Alpha
Classifier: Environment :: Console
Classifier: Intended Audience :: Developers
Classifier: License :: OSI Approved :: The Unlicense (Unlicense)
Classifier: Programming Language :: Python
Classifier: Programming Language :: Python :: 3 :: Only
Classifier: Programming Language :: Python :: 3.12
Classifier: Topic :: Software Development :: Version Control :: Git
Classifier: Topic :: System :: Logging
Requires-Python: >=3.12
Requires-Dist: fake-useragent>=1.5
Requires-Dist: mitmproxy>=11.0
Requires-Dist: pygithub>=2.4
Requires-Dist: pykka>=4.0
Requires-Dist: pyppeteer-stealth>=2.7
Requires-Dist: pyppeteer>=2.0
Requires-Dist: pyxdg>=0.28
Requires-Dist: returns>=0.21
Requires-Dist: rich>=13.9
Requires-Dist: shellingham>=1.5
Requires-Dist: termcolor>=2.5
Requires-Dist: typer>=0.12
Requires-Dist: websockets>=10
